symstore/__init__.py
symstore/cab.py
symstore/command_line.py
symstore/errs.py
symstore/fileio.py
symstore/pdb.py
symstore/pe.py
symstore/symstore.py
symstore-0.3.5.dist-info/entry_points.txt
symstore-0.3.5.dist-info/licenses/LICENSE
symstore-0.3.5.dist-info/WHEEL
symstore-0.3.5.dist-info/METADATA
symstore-0.3.5.dist-info/RECORD
