Metadata-Version: 2.4
Name: symstore
Version: 0.3.5
Summary: publish PDB and PE files to symbols store
Classifier: License :: OSI Approved :: MIT License
Classifier: Intended Audience :: Developers
Classifier: Programming Language :: Python :: 3
Classifier: Programming Language :: Python :: 3.7
Classifier: Programming Language :: Python :: 3.8
Classifier: Programming Language :: Python :: 3.9
Classifier: Programming Language :: Python :: 3.10
Classifier: Programming Language :: Python :: 3.11
Classifier: Programming Language :: Python :: 3.12
Classifier: Programming Language :: Python :: 3.13
License-File: LICENSE
Requires-Dist: pytest ; extra == "dev"
Requires-Dist: pytest-cov ; extra == "dev"
Requires-Dist: coverage ; extra == "dev"
Requires-Dist: flake8 ; extra == "dev"
Project-URL: changelog, https://github.com/symstore/symstore#change-log
Project-URL: documentation, https://github.com/symstore/symstore#readme
Project-URL: homepage, https://github.com/symstore/symstore
Project-URL: repository, https://github.com/symstore/symstore.git
Provides-Extra: dev
